socket_log_receiver/__init__.py
socket_log_receiver/__main__.py
socket_log_receiver/config.py
socket_log_receiver/py.typed
socket_log_receiver/receivers.py
socket_log_receiver-24.3.0b0.dist-info/LICENSE.txt
socket_log_receiver-24.3.0b0.dist-info/METADATA
socket_log_receiver-24.3.0b0.dist-info/WHEEL
socket_log_receiver-24.3.0b0.dist-info/entry_points.txt
socket_log_receiver-24.3.0b0.dist-info/top_level.txt
socket_log_receiver-24.3.0b0.dist-info/RECORD
