Metadata-Version: 2.1
Name: socket-log-receiver
Version: 24.3.0b0
Summary: A light-weight socket log receiver
Author-email: Taro Sato <okomestudio@gmail.com>
Project-URL: Homepage, https://github.com/okomestudio/socket-log-receiver
Project-URL: Buck Tracker, https://github.com/okomestudio/socket-log-receiver/issues
Classifier: Development Status :: 4 - Beta
Classifier: Intended Audience :: Developers
Classifier: License :: OSI Approved :: MIT License
Classifier: Operating System :: POSIX :: Linux
Classifier: Programming Language :: Python :: 3
Classifier: Programming Language :: Python :: 3.8
Classifier: Programming Language :: Python :: 3.9
Classifier: Programming Language :: Python :: 3.10
Classifier: Programming Language :: Python :: 3.11
Classifier: Programming Language :: Python :: 3.12
Classifier: Topic :: Utilities
Requires-Python: >=3.8
License-File: LICENSE.txt
Requires-Dist: resconfig ==20.4.3a0
Provides-Extra: dev
Requires-Dist: mypy ==1.8.0 ; extra == 'dev'
Requires-Dist: pre-commit ==3.6.1 ; extra == 'dev'
Requires-Dist: ruff ==0.2.2 ; extra == 'dev'
Provides-Extra: test
Requires-Dist: coverage[toml] ==7.4.1 ; extra == 'test'
Requires-Dist: pytest ==8.0.1 ; extra == 'test'
Requires-Dist: pytest-cov ==4.1.0 ; extra == 'test'
Requires-Dist: pytest-mock ==3.12.0 ; extra == 'test'
Requires-Dist: pytest-xprocess ==0.23.0 ; extra == 'test'
